ClearJson/Serialization.py
ClearJson/__init__.py
clearjson-1.0.1.dist-info/METADATA
clearjson-1.0.1.dist-info/WHEEL
clearjson-1.0.1.dist-info/licenses/LICENSE
clearjson-1.0.1.dist-info/RECORD
