Metadata-Version: 2.4
Name: ClearJson
Version: 1.0.1
Summary: Utility library for JSON Serialization.
Project-URL: Homepage, https://github.com/bradleydonmorris/ClearJson
Project-URL: Issues, https://github.com/bradleydonmorris/ClearJson/issues
Author-email: Bradley Morris <bradleydonmorris@hotmail.com>
License-File: LICENSE
Classifier: License :: OSI Approved :: MIT License
Classifier: Operating System :: OS Independent
Classifier: Programming Language :: Python :: 3
Requires-Python: >=3.11
